{
    "bounds": [
        {
            "x": 0,
            "y": 0,
            "width": 428,
            "height": 433
        },
        {
            "x": 429,
            "y": 0,
            "width": 428,
            "height": 433
        },
        {
            "x": 852,
            "y": 0,
            "width": 428,
            "height": 433
        },
        {
            "x": 0,
            "y": 430,
            "width": 428,
            "height": 433
        },
        {
            "x": 426,
            "y": 430,
            "width": 428,
            "height": 433
        },
        {
            "x": 852,
            "y": 430,
            "width": 428,
            "height": 338
        }
    ]
}
